Workbook

Sheet Info - danh-muc-2026-03-17 5-1
A1: danh-muc-2026-03-17 5-1
A2: symbol | B2: type | C2: quantity | D2: current_price | E2: total_value | F2: giá trị | G2: tỷ trọng
A3: REE | B3: stock | C3: 2400 | D3: 64000 | E3: 153600000
A4: SJC_1L | B4: gold | C4: 10.8 | D4: 180000000 | E4: 1944000000
A5: MWG | B5: stock | C5: 3900 | D5: 83700 | E5: 326430000
A6: PNJ | B6: stock | C6: 2400 | D6: 115000 | E6: 276000000
A7: MBB | B7: stock | C7: 10000 | D7: 26300 | E7: 263000000
A8: FPT | B8: stock | C8: 3130 | D8: 78600 | E8: 246018000
A9: ACB | B9: stock | C9: 10200 | D9: 23750 | E9: 242250000
A10: VCB | B10: stock | C10: 3400 | D10: 60500 | E10: 205700000
A11: CTG | B11: stock | C11: 4300 | D11: 35000 | E11: 150500000
A12: HPG | B12: stock | C12: 5400 | D12: 26800 | E12: 144720000
A13: DGC | B13: stock | C13: 1500 | D13: 64000 | E13: 96000000
A14: CTR | B14: stock | C14: 1200 | D14: 82500 | E14: 99000000
... A31: TIEU_DUNG | B31: quỹ tiêu dùng | C31: 1 | D31: 1153190000 | E31: 1153190000
A32: Lãi suất tiết kiệm | F32: 0.065
A33: Trượt giá | F33: 0.025
A34: Vàng | F34: 0.08
A35: BDS | F35: 0.12
A36: BDS | F36: 0.12
A37: BDS | F37: 0.1
A38: Ls vay ngắn hạn | F38: {=F32+1.5%} -> 0.08
A39: Ls vay dài hạn | F39: {=F32+4%} -> 0.105
A40: Mạo hiểm | F40: 0.15
A41: Trung bình lợi nhuận | F41: 0.09
A42: Chứng khoán | F42: 0.158
A43: CCQ | F43: 0.12
A44: Cổ phiếu | F44: 0.15
A45: Quỹ ETF | F45: {=F42} -> 0.158
A46: Gold price | F46: {=D4/1000} -> 180000
A47: Usd price | F47: 26700
A48: Tỷ trọng vàng | G48: 0.2
A49: Tỷ trọng crypto | G49: 0.1
A50: Tỷ trọng ccq | G50: 0.1

Sheet Total Asset - Bảng 1
B2: Tổng Tài sản | C2: Tài sản ròng | D2: Nợ | E2: Tiền mặt | F2: Vàng | G2: Quỹ đầu tư | H2: Crypto | I2: Vốn lưu động chưa phân bổ | J2: BDS | K2: KK
L3: Mặt đường 664 | M3: Đất NN Mặt đường | N3: Đất NN 9 ha | O3: NN Iakha | P3: Tiêu sản | Q3: Kho xưởng | R3: Năng lượng MT | S3: Ng Tất Thành
A4: 2025 | B4: 8.879773e+10 | C4: 8.7114451e+10 | D4: -1683278533 | E4: 1220000000 | F4: 1497440000 | G4: 2539348000 | H4: 278176000 | I4: 6.1508455e+09 | K4: 3926037000 | L4: 16080000000 | M4: 10495200000 | N4: 11622500000 | O4: 4138219000 | P4: 1515564000 | Q4: 2992140000 | R4: 1522350000 | S4: 19800000000
A5: 2026 | B5: {=C5-D5} -> 9.1645673e+10 | C5: {=SUM(D5:S5)} -> 8.9962395e+10 | D5: {='Bank - INTEREST & LOAN'!C3} -> -1683278000 | E5: {='Financial fund - CASH'!E3} -> 1065000000 | F5: {='Financial fund - CASH'!H3} -> 2993337720 | G5: {='Financial fund - CASH'!N3+'Financial fund - CASH'!K3} -> 7985071795 | H5: {='Financial fund - CASH'!Q3} -> 1052548425 | I5: {='Cash flow - CASH FLOW'!B3} -> 5.2739457e+08 | K5: {=K4} -> 3926037000 | L5: {=L4*(1+'Info - danh-muc-2026-03-17 5-1'!$F$36)-'Income - Expense - INCOME'!I3} -> 18009600000 | M5: {=M4*(1+'Info - danh-muc-2026-03-17 5-1'!$F$36)} -> 11754624000 | N5: {=N4*(1+'Info - danh-muc-2026-03-17 5-1'!$F$37)} -> 12784750000 | O5: {=O4} -> 4138219000 | P5: {=P4} -> 1515564000 | Q5: {=Q4*(100%-10%)} -> 2692926000 | R5: {=R4-2035000000*5%} -> 1420600000 | S5: {=S4*(1+'Info - danh-muc-2026-03-17 5-1'!$F$37)} -> 21780000000
A6: 2027 | B6: {=C6-D6} -> 1.0036362e+11 | C6: {=SUM(D6:S6)} -> 9.8680339e+10 | D6: {='Bank - INTEREST & LOAN'!C4} -> -1683278000 | E6: {='Financial fund - CASH'!E4} -> 1134225000 | F6: {='Financial fund - CASH'!H4} -> 3.346722e+09 | G6: {='Financial fund - CASH'!N4+'Financial fund - CASH'!K4} -> 9.5347784e+09 | H6: {='Financial fund - CASH'!Q4} -> 1.2710811e+09 | I6: {='Cash flow - CASH FLOW'!B4} -> 3.9735146e+08 | K6: {=K5} -> 3926037000 | L6: {=L5*(1+'Info - danh-muc-2026-03-17 5-1'!$F$36)-'Income - Expense - INCOME'!I4} -> 20170752000 | M6: {=M5*(1+'Info - danh-muc-2026-03-17 5-1'!$F$36)} -> 13165178880 | N6: {=N5*(1+'Info - danh-muc-2026-03-17 5-1'!$F$37)} -> 14063225000 | O6: {=O5} -> 4138219000 | P6: {=P5} -> 1515564000 | Q6: {=Q5*(100%-10%)} -> 2423633400 | R6: {=R5-2035000000*5%} -> 1318850000 | S6: {=S5*(1+'Info - danh-muc-2026-03-17 5-1'!$F$37)} -> 23958000000
A7: 2028 | B7: {=C7-D7} -> 1.101987e+11 | C7: {=SUM(D7:S7)} -> 1.0851542e+11 | D7: {='Bank - INTEREST & LOAN'!C5} -> -1683278000 | E7: {='Financial fund - CASH'!E5} -> 1207949625 | F7: {='Financial fund - CASH'!H5} -> 3.7002876e+09 | G7: {='Financial fund - CASH'!N5+'Financial fund - CASH'!K5} -> 1.1203338e+10 | H7: {='Financial fund - CASH'!Q5} -> 1.5074386e+09 | I7: {='Cash flow - CASH FLOW'!B5} -> 4.4190836e+08 | K7: {=K6} -> 3926037000 | L7: {=L6*(1+'Info - danh-muc-2026-03-17 5-1'!$F$36)-'Income - Expense - INCOME'!I5} -> 22591242240 | M7: {=M6*(1+'Info - danh-muc-2026-03-17 5-1'!$F$36)} -> 1.4745e+10 | N7: {=N6*(1+'Info - danh-muc-2026-03-17 5-1'!$F$37)} -> 15469547500 | O7: {=O6} -> 4138219000 | P7: {=P6} -> 1515564000 | Q7: {=Q6*(100%-10%)} -> 2181270060 | R7: {=R6-2035000000*5%} -> 1217100000 | S7: {=S6*(1+'Info - danh-muc-2026-03-17 5-1'!$F$37)} -> 26353800000
A8: 2029 | B8: {=C8-D8} -> 1.2126983e+11 | C8: {=SUM(D8:S8)} -> 1.1958655e+11 | D8: {='Bank - INTEREST & LOAN'!C6} -> -1683278000 | E8: {='Financial fund - CASH'!E6} -> 1.2864664e+09 | F8: {='Financial fund - CASH'!H6} -> 4.0917629e+09 | G8: {='Financial fund - CASH'!N6+'Financial fund - CASH'!K6} -> 1.314806e+10 | H8: {='Financial fund - CASH'!Q6} -> 1.7843739e+09 | I8: {='Cash flow - CASH FLOW'!B6} -> 4.7857997e+08 | K8: {=K7} -> 3926037000 | L8: {=L7*(1+'Info - danh-muc-2026-03-17 5-1'!$F$36)-'Income - Expense - INCOME'!I6} -> 2.5302191e+10 | M8: {=M7*(1+'Info - danh-muc-2026-03-17 5-1'!$F$36)} -> 1.65144e+10 | N8: {=N7*(1+'Info - danh-muc-2026-03-17 5-1'!$F$37)} -> 17016502250 | O8: {=O7} -> 4138219000 | P8: {=P7} -> 1515564000 | Q8: {=Q7*(100%-10%)} -> 1963143054 | R8: {=R7-2035000000*5%} -> 1115350000 | S8: {=S7*(1+'Info - danh-muc-2026-03-17 5-1'!$F$37)} -> 28989180000
A9: 2030 | B9: {=C9-D9} -> 133754826796 | C9: {=SUM(D9:S9)} -> 132071548796 | D9: {='Bank - INTEREST & LOAN'!C7} -> -1683278000 | E9: {='Financial fund - CASH'!E7} -> 1.3700867e+09 | F9: {='Financial fund - CASH'!H7} -> 4.5224772e+09 | G9: {='Financial fund - CASH'!N7+'Financial fund - CASH'!K7} -> 1.5402904e+10 | H9: {='Financial fund - CASH'!Q7} -> 2.1070667e+09 | I9: {='Cash flow - CASH FLOW'!B7} -> 5.5121022e+08 | K9: {=K8} -> 3926037000 | L9: {=L8*(1+'Info - danh-muc-2026-03-17 5-1'!$F$36)-'Income - Expense - INCOME'!I7} -> 2.8338454e+10 | M9: {=M8*(1+'Info - danh-muc-2026-03-17 5-1'!$F$36)} -> 1.8496128e+10 | N9: {=N8*(1+'Info - danh-muc-2026-03-17 5-1'!$F$37)} -> 18718152475 | O9: {=O8} -> 4138219000 | P9: {=P8} -> 1515564000 | Q9: {=Q8*(100%-10%)} -> 1.7668287e+09 | R9: {=R8-2035000000*5%} -> 1013600000 | S9: {=S8*(1+'Info - danh-muc-2026-03-17 5-1'!$F$37)} -> 31888098000
A10: 2031 | B10: {=C10-D10} -> 1.477574e+11 | C10: {=SUM(D10:S10)} -> 1.4607413e+11 | D10: {='Bank - INTEREST & LOAN'!C8} -> -1683278000 | E10: {='Financial fund - CASH'!E8} -> 1.4591423e+09 | F10: {='Financial fund - CASH'!H8} -> 5.0033367e+09 | G10: {='Financial fund - CASH'!N8+'Financial fund - CASH'!K8} -> 1.8041899e+10 | H10: {='Financial fund - CASH'!Q8} -> 2.4865159e+09 | I10: {='Cash flow - CASH FLOW'!B8} -> 5.630857e+08 | K10: {=K9} -> 3926037000 | L10: {=L9*(1+'Info - danh-muc-2026-03-17 5-1'!$F$36)-'Income - Expense - INCOME'!I8} -> 3.1739069e+10 | M10: {=M9*(1+'Info - danh-muc-2026-03-17 5-1'!$F$36)} -> 2.0715664e+10 | N10: {=N9*(1+'Info - danh-muc-2026-03-17 5-1'!$F$37)} -> 2.0589968e+10 | O10: {=O9} -> 4138219000 | P10: {=P9} -> 1515564000 | Q10: {=Q9*(100%-10%)} -> 1.5901459e+09 | R10: {=R9-2035000000*5%} -> 911850000 | S10: {=S9*(1+'Info - danh-muc-2026-03-17 5-1'!$F$37)} -> 35076907800
A11: 2032 | B11: {=C11-D11} -> 1.6345537e+11 | C11: {=SUM(D11:S11)} -> 1.617721e+11 | D11: {='Bank - INTEREST & LOAN'!C9} -> -1683278000 | E11: {='Financial fund - CASH'!E9} -> 1.5539865e+09 | F11: {='Financial fund - CASH'!H9} -> 5.5252302e+09 | G11: {='Financial fund - CASH'!N9+'Financial fund - CASH'!K9} -> 2.1072559e+10 | H11: {='Financial fund - CASH'!Q9} -> 2.9242481e+09 | I11: {='Cash flow - CASH FLOW'!B9} -> 5.7543621e+08 | K11: {=K10} -> 3926037000 | L11: {=L10*(1+'Info - danh-muc-2026-03-17 5-1'!$F$36)-'Income - Expense - INCOME'!I9} -> 3.5547757e+10 | M11: {=M10*(1+'Info - danh-muc-2026-03-17 5-1'!$F$36)} -> 2.3201544e+10 | N11: {=N10*(1+'Info - danh-muc-2026-03-17 5-1'!$F$37)} -> 2.2648964e+10 | O11: {=O10} -> 4138219000 | P11: {=P10} -> 1515564000 | Q11: {=Q10*(100%-10%)} -> 1.4311313e+09 | R11: {=R10-2035000000*5%} -> 810100000 | S11: {=S10*(1+'Info - danh-muc-2026-03-17 5-1'!$F$37)} -> 38584598580
A12: 2033 | B12: {=C12-D12} -> 1.8104891e+11 | C12: {=SUM(D12:S12)} -> 1.7936563e+11 | D12: {='Bank - INTEREST & LOAN'!C10} -> -1683278000 | E12: {='Financial fund - CASH'!E10} -> 1.6549957e+09 | F12: {='Financial fund - CASH'!H10} -> 6.0915428e+09 | G12: {='Financial fund - CASH'!N10+'Financial fund - CASH'!K10} -> 2.4552706e+10 | H12: {='Financial fund - CASH'!Q10} -> 3.4290605e+09 | I12: {='Cash flow - CASH FLOW'!B10} -> 5.8828074e+08 | K12: {=K11} -> 3926037000 | L12: {=L11*(1+'Info - danh-muc-2026-03-17 5-1'!$F$36)-'Income - Expense - INCOME'!I10} -> 3.9813488e+10 | M12: {=M11*(1+'Info - danh-muc-2026-03-17 5-1'!$F$36)} -> 2.5985729e+10 | N12: {=N11*(1+'Info - danh-muc-2026-03-17 5-1'!$F$37)} -> 2.4913861e+10 | O12: {=O11} -> 4138219000 | P12: {=P11} -> 1515564000 | Q12: {=Q11*(100%-10%)} -> 1.2880182e+09 | R12: {=R11-2035000000*5%} -> 708350000 | S12: {=S11*(1+'Info - danh-muc-2026-03-17 5-1'!$F$37)} -> 42443058438
A13: 2034 | B13: {=C13-D13} -> 2.0076331e+11 | C13: {=SUM(D13:S13)} -> 1.9908004e+11 | D13: {='Bank - INTEREST & LOAN'!C11} -> -1683278000 | E13: {='Financial fund - CASH'!E11} -> 1.7625704e+09 | F13: {='Financial fund - CASH'!H11} -> 6.7059349e+09 | G13: {='Financial fund - CASH'!N11+'Financial fund - CASH'!K11} -> 2.8548728e+10 | H13: {='Financial fund - CASH'!Q11} -> 4.0110718e+09 | I13: {='Cash flow - CASH FLOW'!B11} -> 6.0163905e+08 | K13: {=K12} -> 3926037000 | L13: {=L12*(1+'Info - danh-muc-2026-03-17 5-1'!$F$36)-'Income - Expense - INCOME'!I11} -> 4.4591106e+10 | M13: {=M12*(1+'Info - danh-muc-2026-03-17 5-1'!$F$36)} -> 2.9104016e+10 | N13: {=N12*(1+'Info - danh-muc-2026-03-17 5-1'!$F$37)} -> 2.7405247e+10 | O13: {=O12} -> 4138219000 | P13: {=P12} -> 1515564000 | Q13: {=Q12*(100%-10%)} -> 1.1592163e+09 | R13: {=R12-2035000000*5%} -> 606600000 | S13: {=S12*(1+'Info - danh-muc-2026-03-17 5-1'!$F$37)} -> 4.6687364e+10
A14: 2035 | B14: {=C14-D14} -> 2.2285219e+11 | C14: {=SUM(D14:S14)} -> 2.2116891e+11 | D14: {='Bank - INTEREST & LOAN'!C12} -> -1683278000 | E14: {='Financial fund - CASH'!E12} -> 1.8771375e+09 | F14: {='Financial fund - CASH'!H12} -> 7.3723637e+09 | G14: {='Financial fund - CASH'!N12+'Financial fund - CASH'!K12} -> 3.3136857e+10 | H14: {='Financial fund - CASH'!Q12} -> 4.6819211e+09 | I14: {='Cash flow - CASH FLOW'!B12} -> 6.1553169e+08 | K14: {=K13} -> 3926037000 | L14: {=L13*(1+'Info - danh-muc-2026-03-17 5-1'!$F$36)-'Income - Expense - INCOME'!I12} -> 4.9942039e+10 | M14: {=M13*(1+'Info - danh-muc-2026-03-17 5-1'!$F$36)} -> 3.2596498e+10 | N14: {=N13*(1+'Info - danh-muc-2026-03-17 5-1'!$F$37)} -> 3.0145772e+10 | O14: {=O13} -> 4138219000 | P14: {=P13} -> 1515564000 | Q14: {=Q13*(100%-10%)} -> 1.0432947e+09 | R14: {=R13-2035000000*5%} -> 504850000 | S14: {=S13*(1+'Info - danh-muc-2026-03-17 5-1'!$F$37)} -> 5.1356101e+10
A15: 2036 | B15: {=C15-D15} -> 2.4760097e+11 | C15: {=SUM(D15:S15)} -> 2.4591769e+11 | D15: {='Bank - INTEREST & LOAN'!C13} -> -1683278000 | E15: {='Financial fund - CASH'!E13} -> 1.9991514e+09 | F15: {='Financial fund - CASH'!H13} -> 8.0951077e+09 | G15: {='Financial fund - CASH'!N13+'Financial fund - CASH'!K13} -> 3.8404631e+10 | H15: {='Financial fund - CASH'!Q13} -> 5.4549954e+09 | I15: {='Cash flow - CASH FLOW'!B13} -> 6.2998003e+08 | K15: {=K14} -> 3926037000 | L15: {=L14*(1+'Info - danh-muc-2026-03-17 5-1'!$F$36)-'Income - Expense - INCOME'!I13} -> 5.5935084e+10 | M15: {=M14*(1+'Info - danh-muc-2026-03-17 5-1'!$F$36)} -> 3.6508078e+10 | N15: {=N14*(1+'Info - danh-muc-2026-03-17 5-1'!$F$37)} -> 3.3160349e+10 | O15: {=O14} -> 4138219000 | P15: {=P14} -> 1515564000 | Q15: {=Q14*(100%-10%)} -> 9.3896524e+08 | R15: {=R14-2035000000*5%} -> 403100000 | S15: {=S14*(1+'Info - danh-muc-2026-03-17 5-1'!$F$37)} -> 5.6491711e+10
A16: 2037 | B16: {=C16-D16} -> 2.7533101e+11 | C16: {=SUM(D16:S16)} -> 2.7364773e+11 | D16: {='Bank - INTEREST & LOAN'!C14} -> -1683278000 | E16: {='Financial fund - CASH'!E14} -> 2.1290962e+09 | F16: {='Financial fund - CASH'!H14} -> 8.878792e+09 | G16: {='Financial fund - CASH'!N14+'Financial fund - CASH'!K14} -> 4.4452579e+10 | H16: {='Financial fund - CASH'!Q14} -> 6.3456924e+09 | I16: {='Cash flow - CASH FLOW'!B14} -> 6.4500631e+08 | K16: {=K15} -> 3926037000 | L16: {=L15*(1+'Info - danh-muc-2026-03-17 5-1'!$F$36)-'Income - Expense - INCOME'!I14} -> 6.2647294e+10 | M16: {=M15*(1+'Info - danh-muc-2026-03-17 5-1'!$F$36)} -> 4.0889047e+10 | N16: {=N15*(1+'Info - danh-muc-2026-03-17 5-1'!$F$37)} -> 3.6476384e+10 | O16: {=O15} -> 4138219000 | P16: {=P15} -> 1515564000 | Q16: {=Q15*(100%-10%)} -> 8.4506871e+08 | R16: {=R15-2035000000*5%} -> 301350000 | S16: {=S15*(1+'Info - danh-muc-2026-03-17 5-1'!$F$37)} -> 6.2140882e+10
... A18: 2039 | B18: {=C18-D18} -> 3.4115195e+11 | C18: {=SUM(D18:S18)} -> 3.3946867e+11 | D18: {='Bank - INTEREST & LOAN'!C16} -> -1683278000 | E18: {='Financial fund - CASH'!E16} -> 2.4148742e+09 | F18: {='Financial fund - CASH'!H16} -> 1.0641713e+10 | G18: {='Financial fund - CASH'!N16+'Financial fund - CASH'!K16} -> 5.9339582e+10 | H18: {='Financial fund - CASH'!Q16} -> 8.5493678e+09 | I18: {='Cash flow - CASH FLOW'!B16} -> 6.4136092e+08 | K18: {=K17} -> 3926037000 | L18: {=L17*(1+'Info - danh-muc-2026-03-17 5-1'!$F$36)-'Income - Expense - INCOME'!I16} -> 7.8584766e+10 | M18: {=M17*(1+'Info - danh-muc-2026-03-17 5-1'!$F$36)} -> 5.1291221e+10 | N18: {=N17*(1+'Info - danh-muc-2026-03-17 5-1'!$F$37)} -> 4.4136424e+10 | O18: {=O17} -> 4138219000 | P18: {=P17} -> 1515564000 | Q18: {=Q17*(100%-10%)} -> 6.8450566e+08 | R18: {=R17-2035000000*5%} -> 97850000 | S18: {=S17*(1+'Info - danh-muc-2026-03-17 5-1'!$F$37)} -> 7.5190467e+10
A19: 2040 | B19: {=C19-D19} -> 3.8014331e+11 | C19: {=SUM(D19:S19)} -> 3.7846003e+11 | D19: {='Bank - INTEREST & LOAN'!C17} -> -1683278000 | E19: {='Financial fund - CASH'!E17} -> 2.571841e+09 | F19: {='Financial fund - CASH'!H17} -> 1.1631584e+10 | G19: {='Financial fund - CASH'!N17+'Financial fund - CASH'!K17} -> 6.8459528e+10 | H19: {='Financial fund - CASH'!Q17} -> 9.9055294e+09 | I19: {='Cash flow - CASH FLOW'!B17} -> 6.5826344e+08 | K19: {=K18} -> 3926037000 | L19: {=L18*(1+'Info - danh-muc-2026-03-17 5-1'!$F$36)-'Income - Expense - INCOME'!I17} -> 8.8014937e+10 | M19: {=M18*(1+'Info - danh-muc-2026-03-17 5-1'!$F$36)} -> 5.7446167e+10 | N19: {=N18*(1+'Info - danh-muc-2026-03-17 5-1'!$F$37)} -> 4.8550067e+10 | O19: {=O18} -> 4138219000 | P19: {=P18} -> 1515564000 | Q19: {=Q18*(100%-10%)} -> 6.1605509e+08 | S19: {=S18*(1+'Info - danh-muc-2026-03-17 5-1'!$F$37)} -> 8.2709514e+10
A20: 2041 | B20: {=C20-D20} -> 4.2395282e+11 | C20: {=SUM(D20:S20)} -> 4.2226954e+11 | D20: {='Bank - INTEREST & LOAN'!C18} -> -1683278000 | E20: {='Financial fund - CASH'!E18} -> 2.7390107e+09 | F20: {='Financial fund - CASH'!H18} -> 1.2704296e+10 | G20: {='Financial fund - CASH'!N18+'Financial fund - CASH'!K18} -> 7.8930368e+10 | H20: {='Financial fund - CASH'!Q18} -> 1.1467059e+10 | I20: {='Cash flow - CASH FLOW'!B18} -> 6.7584206e+08 | K20: {=K19} -> 3926037000 | L20: {=L19*(1+'Info - danh-muc-2026-03-17 5-1'!$F$36)-'Income - Expense - INCOME'!I18} -> 9.857673e+10 | M20: {=M19*(1+'Info - danh-muc-2026-03-17 5-1'!$F$36)} -> 6.4339707e+10 | N20: {=N19*(1+'Info - danh-muc-2026-03-17 5-1'!$F$37)} -> 5.3405074e+10 | O20: {=O19} -> 4138219000 | P20: {=P19} -> 1515564000 | Q20: {=Q19*(100%-10%)} -> 5.5444958e+08 | S20: {=S19*(1+'Info - danh-muc-2026-03-17 5-1'!$F$37)} -> 9.0980465e+10
A21: 2042 | B21: {=C21-D21} -> 4.7306437e+11 | C21: {=SUM(D21:S21)} -> 4.7138109e+11 | D21: {='Bank - INTEREST & LOAN'!C19} -> -1683278000 | E21: {='Financial fund - CASH'!E19} -> 2.9170464e+09 | F21: {='Financial fund - CASH'!H19} -> 1.3866622e+10 | G21: {='Financial fund - CASH'!N19+'Financial fund - CASH'!K19} -> 9.095241e+10 | H21: {='Financial fund - CASH'!Q19} -> 1.326484e+10 | I21: {='Cash flow - CASH FLOW'!B19} -> 6.9412383e+08 | K21: {=K20} -> 3926037000 | L21: {=L20*(1+'Info - danh-muc-2026-03-17 5-1'!$F$36)-'Income - Expense - INCOME'!I19} -> 1.1040594e+11 | M21: {=M20*(1+'Info - danh-muc-2026-03-17 5-1'!$F$36)} -> 7.2060472e+10 | N21: {=N20*(1+'Info - danh-muc-2026-03-17 5-1'!$F$37)} -> 5.8745581e+10 | O21: {=O20} -> 4138219000 | P21: {=P20} -> 1515564000 | Q21: {=Q20*(100%-10%)} -> 4.9900462e+08 | S21: {=S20*(1+'Info - danh-muc-2026-03-17 5-1'!$F$37)} -> 1.0007851e+11
A22: 2043 | B22: {=C22-D22} -> 5.2813364e+11 | C22: {=SUM(D22:S22)} -> 5.2645036e+11 | D22: {='Bank - INTEREST & LOAN'!C20} -> -1683278000 | E22: {='Financial fund - CASH'!E20} -> 3.1066544e+09 | F22: {='Financial fund - CASH'!H20} -> 1.5125882e+10 | G22: {='Financial fund - CASH'!N20+'Financial fund - CASH'!K20} -> 1.0475577e+11 | H22: {='Financial fund - CASH'!Q20} -> 1.533439e+10 | I22: {='Cash flow - CASH FLOW'!B20} -> 7.1313687e+08 | K22: {=K21} -> 3926037000 | L22: {=L21*(1+'Info - danh-muc-2026-03-17 5-1'!$F$36)-'Income - Expense - INCOME'!I20} -> 1.2365465e+11 | M22: {=M21*(1+'Info - danh-muc-2026-03-17 5-1'!$F$36)} -> 8.0707729e+10 | N22: {=N21*(1+'Info - danh-muc-2026-03-17 5-1'!$F$37)} -> 6.4620139e+10 | O22: {=O21} -> 4138219000 | P22: {=P21} -> 1515564000 | Q22: {=Q21*(100%-10%)} -> 4.4910416e+08 | S22: {=S21*(1+'Info - danh-muc-2026-03-17 5-1'!$F$37)} -> 1.1008636e+11
A23: 2044 | B23: {=C23-D23} -> 5.8989989e+11 | C23: {=SUM(D23:S23)} -> 5.8821661e+11 | D23: {='Bank - INTEREST & LOAN'!C21} -> -1683278000 | E23: {='Financial fund - CASH'!E21} -> 3.3085869e+09 | F23: {='Financial fund - CASH'!H21} -> 1.648999e+10 | G23: {='Financial fund - CASH'!N21+'Financial fund - CASH'!K21} -> 1.2060481e+11 | H23: {='Financial fund - CASH'!Q21} -> 1.7716559e+10 | I23: {='Cash flow - CASH FLOW'!B21} -> 7.3291043e+08 | K23: {=K22} -> 3926037000 | L23: {=L22*(1+'Info - danh-muc-2026-03-17 5-1'!$F$36)-'Income - Expense - INCOME'!I21} -> 1.3849321e+11 | M23: {=M22*(1+'Info - danh-muc-2026-03-17 5-1'!$F$36)} -> 9.0392656e+10 | N23: {=N22*(1+'Info - danh-muc-2026-03-17 5-1'!$F$37)} -> 7.1082153e+10 | O23: {=O22} -> 4138219000 | P23: {=P22} -> 1515564000 | Q23: {=Q22*(100%-10%)} -> 4.0419375e+08 | S23: {=S22*(1+'Info - danh-muc-2026-03-17 5-1'!$F$37)} -> 1.21095e+11

Sheet Investment - INDIVIDUAL STOCK
A1: INDIVIDUAL STOCK
A2: tài sản | B2: loại | C2: Current | D2: Interest | E2: Cost of Capital | F2: Nhập | G2: 2025 | H2: Ql | I2: Current price | J2: TCBS | K2: Fmarket | L2: vinaMIO | M2: Ledger | N2: Binance
A3: MWG | C3: {=H3*I3} -> 326430000 | D3: {=C3-E3} -> -19550000 | E3: {=G3+F3} -> 345980000 | F3: 107300000 | G3: 238680000 | H3: 3900 | I3: 83700
A4: PNJ | C4: {=H4*I4} -> 276000000 | D4: {=C4-E4} -> 43200000 | E4: {=G4+F4} -> 232800000 | F4: 0 | G4: 232800000 | H4: 2400 | I4: 115000
A5: MBB | C5: {=H5*I5} -> 263000000 | D5: {=C5-E5} -> 10000000 | E5: {=G5+F5} -> 253000000 | F5: 0 | G5: 253000000 | H5: 10000 | I5: 26300
A6: FPT | C6: {=H6*I6} -> 246018000 | D6: {=C6-E6} -> -43476000 | E6: {=G6+F6} -> 289494000 | F6: 104600000 | G6: 184894000 | H6: 3130 | I6: 78600
A7: ACB | C7: {=H7*I7} -> 242250000 | D7: {=C7-E7} -> -4050000 | E7: {=G7+F7} -> 246300000 | F7: 49500000 | G7: 196800000 | H7: 10200 | I7: 23750
A8: VCB | C8: {=H8*I8} -> 205700000 | D8: {=C8-E8} -> 4100000 | E8: {=SUM(F8,G8)} -> 201600000 | F8: 98100000 | G8: 103500000 | H8: 3400 | I8: 60500
A9: CTG | C9: {=H9*I9} -> 150500000 | D9: {=C9-E9} -> -7025000 | E9: {=F9+G9} -> 157525000 | F9: 103900000 | G9: 53625000 | H9: 4300 | I9: 35000
A10: REE | C10: {=H10*I10} -> 153600000 | D10: {=C10-E10} -> 7600000 | E10: {=F10+G10} -> 146000000 | F10: 103300000 | G10: 42700000 | H10: 2400 | I10: 64000
A11: HPG | C11: {=H11*I11} -> 144720000 | D11: {=C11-E11} -> 1920000 | E11: {=SUM(F11,G11)} -> 142800000 | F11: 50400000 | G11: 92400000 | H11: {=3500+1900} -> 5400 | I11: 26800
A12: DGC | C12: {=H12*I12} -> 96000000 | D12: {=C12-E12} -> -6750000 | E12: {=SUM(F12,G12)} -> 102750000 | F12: 0 | G12: 102750000 | H12: 1500 | I12: 64000
A13: CTR | C13: {=H13*I13} -> 99000000 | D13: {=C13-E13} -> -3360000 | E13: {=F13+G13} -> 102360000 | F13: 0 | G13: 102360000 | H13: 1200 | I13: 82500
A14: TCB | C14: {=H14*I14} -> 90900000 | D14: {=C14-E14} -> -14500000 | E14: {=F14+G14} -> 105400000 | F14: 105400000 | G14: 0 | H14: 3000 | I14: 30300
A15: BMP | C15: {=H15*I15} -> 82020000 | D15: {=C15-E15} -> -17180000 | E15: {=F15+G15} -> 99200000 | F15: 29200000 | G15: 70000000 | H15: 600 | I15: 136700
A16: SSI | C16: {=H16*I16} -> 47600000 | D16: {=C16-E16} -> -4900000 | E16: {=F16+G16} -> 52500000 | F16: 52500000 | G16: 0 | H16: 1700 | I16: 28000
A17: VCBFIF | B17: Bond | C17: {=SUM(J17:L17)} -> 312000000 | D17: {=C17-E17} -> -44570000 | E17: {=G17+F17} -> 356570000 | F17: 0 | G17: 356570000 | J17: 312000000
A18: VESAF | B18: Stock | C18: {=SUM(J18:L18)} -> 155579000 | D18: {=C18-E18} -> 11001000 | E18: {=G18+F18} -> 144578000 | F18: 30000000 | G18: 114578000 | J18: 107000000 | L18: 48579000
A19: SSISCA | B19: Stock | C19: {=SUM(J19:L19)} -> 153000000 | D19: {=C19-E19} -> 8442000 | E19: {=G19+F19} -> 144558000 | F19: 30000000 | G19: 114558000 | J19: 153000000
A20: VCBMGF | B20: Stock | C20: {=SUM(J20:L20)} -> 195486000 | D20: {=C20-E20} -> 57673000 | E20: {=G20+F20} -> 137813000 | F20: 30000000 | G20: 107813000 | J20: 118000000 | K20: 77486000
A21: VMEEF | B21: Stock | C21: {=SUM(J21:L21)} -> 117258000 | D21: {=C21-E21} -> 6897000 | E21: {=G21+F21} -> 110361000 | F21: 30000000 | G21: 80361000 | J21: 30000000 | K21: 37446000 | L21: 49812000
A22: TCBF | B22: Bond | C22: {=SUM(J22:L22)} -> 69000000 | D22: {=C22-E22} -> 844000 | E22: {=G22+F22} -> 68156000 | F22: 0 | G22: 68156000 | J22: 69000000
A23: DCDS | B23: Stock | C23: {=SUM(J23:L23)} -> 41000000 | D23: {=C23-E23} -> 1050000 | E23: {=G23+F23} -> 39950000 | F23: 30000000 | G23: 9950000 | J23: 41000000
A24: VEOF | B24: Stock | C24: {=SUM(J24:L24)} -> 15000000 | D24: {=C24-E24} -> 1147000 | E24: {=G24+F24} -> 13853000 | F24: 0 | G24: 13853000 | J24: 15000000
A25: BTC | C25: {=H25*I25} -> 1.7721949e+08 | D25: {=C25-E25} -> -8295424.8 | E25: {=G25+F25} -> 185514913 | F25: 30601513 | G25: 154913400 | H25: {=SUMIF('Info - danh-muc-2026-03-17 5-1'!$A$3:$A$33,$A25,'Info - danh-muc-2026-03-17 5-1'!$C$3:$C$33)} -> 0.091 | I25: {=SUMIF('Info - danh-muc-2026-03-17 5-1'!$A$3:$A$33,$A25,'Info - danh-muc-2026-03-17 5-1'!$D$3:$D$33)} -> 1947466903 | M25: 6625.57
A26: PAXG | C26: {=H26*I26} -> 1.1716787e+08 | D26: {=C26-E26} -> 8071671.7 | E26: {=G26+F26} -> 109096200 | F26: 0 | G26: 109096200 | H26: {=SUMIF('Info - danh-muc-2026-03-17 5-1'!$A$3:$A$33,$A26,'Info - danh-muc-2026-03-17 5-1'!$C$3:$C$33)} -> 0.896 | I26: {=SUMIF('Info - danh-muc-2026-03-17 5-1'!$A$3:$A$33,$A26,'Info - danh-muc-2026-03-17 5-1'!$D$3:$D$33)} -> 130767714 | M26: 4459 | N26: 244
A27: ETH | C27: {=H27*I27} -> 51710624 | D27: {=C27-E27} -> -13143676 | E27: {=G27+F27} -> 64854300 | F27: 0 | G27: 64854300 | H27: {=SUMIF('Info - danh-muc-2026-03-17 5-1'!$A$3:$A$33,$A27,'Info - danh-muc-2026-03-17 5-1'!$C$3:$C$33)} -> 0.846 | I27: {=SUMIF('Info - danh-muc-2026-03-17 5-1'!$A$3:$A$33,$A27,'Info - danh-muc-2026-03-17 5-1'!$D$3:$D$33)} -> 61123669 | M27: {=1070+524} -> 1594 | N27: 49
A28: SOL | C28: {=H28*I28} -> 10659160 | D28: {=C28-E28} -> -3705440 | E28: {=G28+F28} -> 14364600 | F28: 0 | G28: 14364600 | H28: {=SUMIF('Info - danh-muc-2026-03-17 5-1'!$A$3:$A$33,$A28,'Info - danh-muc-2026-03-17 5-1'!$C$3:$C$33)} -> 4.302 | I28: {=SUMIF('Info - danh-muc-2026-03-17 5-1'!$A$3:$A$33,$A28,'Info - danh-muc-2026-03-17 5-1'!$D$3:$D$33)} -> 2477722 | N28: 337
A29: XRP | C29: {=H29*I29} -> 9664368.8 | D29: {=C29-E29} -> -2430731.2 | E29: {=G29+F29} -> 12095100 | F29: 0 | G29: 12095100 | H29: {=SUMIF('Info - danh-muc-2026-03-17 5-1'!$A$3:$A$33,$A29,'Info - danh-muc-2026-03-17 5-1'!$C$3:$C$33)} -> 242.318 | I29: {=SUMIF('Info - danh-muc-2026-03-17 5-1'!$A$3:$A$33,$A29,'Info - danh-muc-2026-03-17 5-1'!$D$3:$D$33)} -> 39883 | N29: 329
A30: BNB | C30: {=H30*I30} -> 8223929 | D30: {=C30-E30} -> -2482771 | E30: {=G30+F30} -> 10706700 | F30: 0 | G30: 10706700 | H30: {=SUMIF('Info - danh-muc-2026-03-17 5-1'!$A$3:$A$33,$A30,'Info - danh-muc-2026-03-17 5-1'!$C$3:$C$33)} -> 0.464 | I30: {=SUMIF('Info - danh-muc-2026-03-17 5-1'!$A$3:$A$33,$A30,'Info - danh-muc-2026-03-17 5-1'!$D$3:$D$33)} -> 17723985 | N30: 280
A31: AVAX | C31: {=H31*I31} -> 7826401 | D31: {=C31-E31} -> -1892399 | E31: {=G31+F31} -> 9718800 | F31: 0 | G31: 9718800 | H31: {=SUMIF('Info - danh-muc-2026-03-17 5-1'!$A$3:$A$33,$A31,'Info - danh-muc-2026-03-17 5-1'!$C$3:$C$33)} -> 29.074 | I31: {=SUMIF('Info - danh-muc-2026-03-17 5-1'!$A$3:$A$33,$A31,'Info - danh-muc-2026-03-17 5-1'!$D$3:$D$33)} -> 269189 | N31: 256
A32: ADA | C32: {=H32*I32} -> 4971301.9 | D32: {=C32-E32} -> -1116298.1 | E32: {=G32+F32} -> 6087600 | F32: 0 | G32: 6087600 | H32: {=SUMIF('Info - danh-muc-2026-03-17 5-1'!$A$3:$A$33,$A32,'Info - danh-muc-2026-03-17 5-1'!$C$3:$C$33)} -> 651.452 | I32: {=SUMIF('Info - danh-muc-2026-03-17 5-1'!$A$3:$A$33,$A32,'Info - danh-muc-2026-03-17 5-1'!$D$3:$D$33)} -> 7631.11 | N32: 170
A33: LINK | C33: {=H33*I33} -> 4312200.3 | D33: {=C33-E33} -> -1214699.7 | E33: {=G33+F33} -> 5526900 | F33: 0 | G33: 5526900 | H33: {=SUMIF('Info - danh-muc-2026-03-17 5-1'!$A$3:$A$33,$A33,'Info - danh-muc-2026-03-17 5-1'!$C$3:$C$33)} -> 16.717 | I33: {=SUMIF('Info - danh-muc-2026-03-17 5-1'!$A$3:$A$33,$A33,'Info - danh-muc-2026-03-17 5-1'!$D$3:$D$33)} -> 257953 | N33: 140
A34: DOT | C34: {=H34*I34} -> 2766534 | D34: {=C34-E34} -> -303966 | E34: {=G34+F34} -> 3070500 | F34: 0 | G34: 3070500 | H34: {=SUMIF('Info - danh-muc-2026-03-17 5-1'!$A$3:$A$33,$A34,'Info - danh-muc-2026-03-17 5-1'!$C$3:$C$33)} -> 64.338 | I34: {=SUMIF('Info - danh-muc-2026-03-17 5-1'!$A$3:$A$33,$A34,'Info - danh-muc-2026-03-17 5-1'!$D$3:$D$33)} -> 43000 | N34: 81
A35: USDC | C35: {=H35*I35} -> 0 | D35: {=C35-E35} -> -560700 | E35: {=G35+F35} -> 560700 | F35: 0 | G35: 560700 | H35: {=SUMIF('Info - danh-muc-2026-03-17 5-1'!$A$3:$A$33,$A35,'Info - danh-muc-2026-03-17 5-1'!$C$3:$C$33)} -> 0 | I35: {=SUMIF('Info - danh-muc-2026-03-17 5-1'!$A$3:$A$33,$A35,'Info - danh-muc-2026-03-17 5-1'!$D$3:$D$33)} -> 0 | M35: 13 | N35: 0

Sheet Investment - BẢNG ĐẦU TƯ
A1: BẢNG ĐẦU TƯ
B2: Cuối 2023 | C2: 2024 | D2: Chưa thực hiện
A3: Trái phiếu | B3: {=SUM(B4:B5)} -> 200000 | C3: {='Financial fund - CASH'!L3} -> 1061810500 | D3: {=C3-B3} -> 1061610500
A4: DCBF | B4: 200000
A5: Fmarket | B5: 0
A6: Cổ phiếu | B6: {=SUM(B7:B9)} | C6: {=SUM(C7:C9)} | D6: {=C6-B6}
A7: CCQ Vesaf | B7: {=500000} -> 500000 | C7: {=#REF!} | D7: {=C7-B7}
A8: ETF | B8: 0 | C8: {=#REF!} | D8: {=C8-B8}
A9: CP đơn lẻ | B9: {=#REF!+#REF!} | C9: {=#REF!} | D9: {=C9-B9}
B10: {=B3+B6} | C10: {=C3+C6} | D10: {=D3+D6}

Sheet Cash flow - CASH FLOW
A1: CASH FLOW
A2: Năm | B2: Chưa phân bổ | C2: Vốn lưu động | D2: CASH | E2: INCOME | F2: OTHER INCOME | G2: TIÊU DÙNG | H2: INTEREST | I2: OTHER EXPENSE | J2: Tổng đầu tư | K2: Gold | L2: Crypto | M2: Bond | N2: Stock
A3: 2026 | B3: {=6150845000+H3+I3-J3-D3+F3+G3+E3} -> 5.2739457e+08 | C3: 1000000000 | D3: -220000000 | E3: {='Income - Expense - INCOME'!B3} -> 2.0246486e+09 | F3: {='Income - Expense - INCOME'!C3} -> 0 | G3: {=-E3*70%} -> -1.417254e+09 | H3: {='Bank - INTEREST & LOAN'!B3} -> -80000000 | I3: {='Income - Expense - INCOME'!K3} -> 0 | J3: {=6150845000-D3} -> 6370845000 | K3: {=IF(J3<0,0,J3*'Info - danh-muc-2026-03-17 5-1'!$G$48)} -> 1274169000 | L3: {=IF(J3<0,0,J3*'Info - danh-muc-2026-03-17 5-1'!$G$49)} -> 637084500 | M3: {='Info - danh-muc-2026-03-17 5-1'!$G$50*J3} -> 637084500 | N3: {=IF(J3<0,0,J3-K3-L3-M3)} -> 3822507000
A4: 2027 | B4: {=B3+H4+I4-J4-D4+F4+G4+E4} -> 3.9735146e+08 | C4: 1000000000 | D4: {=-C3+C4} -> 0 | E4: {='Income - Expense - INCOME'!B4} -> 2.058698e+09 | F4: {='Income - Expense - INCOME'!C4} -> 0 | G4: {=-E4*70%} -> -1.4410886e+09 | H4: {='Bank - INTEREST & LOAN'!B4} -> -220257950 | I4: {='Income - Expense - INCOME'!K4} -> 0 | J4: {=B3-D4} -> 5.2739457e+08 | K4: {=IF(J4<0,0,J4*'Info - danh-muc-2026-03-17 5-1'!$G$48)} -> 1.0547891e+08 | L4: {=IF(J4<0,0,J4*'Info - danh-muc-2026-03-17 5-1'!$G$49)} -> 52739457 | M4: {='Info - danh-muc-2026-03-17 5-1'!$G$50*J4} -> 52739457 | N4: {=J4-K4-L4-M4} -> 3.1643674e+08
A5: 2028 | B5: {=B4+H5+I5-J5-D5+F5+G5+E5} -> 4.4190836e+08 | C5: 1000000000 | D5: {=-C4+C5} -> 0 | E5: {='Income - Expense - INCOME'!B5} -> 2.207221e+09 | F5: {='Income - Expense - INCOME'!C5} -> 0 | G5: {=-E5*70%} -> -1.5450547e+09 | H5: {='Bank - INTEREST & LOAN'!B5} -> -220257950 | I5: {='Income - Expense - INCOME'!K5} -> 0 | J5: {=B4-D5} -> 3.9735146e+08 | K5: {=IF(J5<0,0,J5*'Info - danh-muc-2026-03-17 5-1'!$G$48)} -> 79470293 | L5: {=IF(J5<0,0,J5*'Info - danh-muc-2026-03-17 5-1'!$G$49)} -> 39735146 | M5: {='Info - danh-muc-2026-03-17 5-1'!$G$50*J5} -> 39735146 | N5: {=J5-K5-L5-M5} -> 2.3841088e+08
A6: 2029 | B6: {=B5+H6+I6-J6-D6+F6+G6+E6} -> 4.7857997e+08 | C6: 1000000000 | D6: {=-C5+C6} -> 0 | E6: {='Income - Expense - INCOME'!B6} -> 2.3294597e+09 | F6: {='Income - Expense - INCOME'!C6} -> 0 | G6: {=-E6*70%} -> -1.6306218e+09 | H6: {='Bank - INTEREST & LOAN'!B6} -> -220257950 | I6: {='Income - Expense - INCOME'!K6} -> 0 | J6: {=B5-D6} -> 4.4190836e+08 | K6: {=IF(J6<0,0,J6*'Info - danh-muc-2026-03-17 5-1'!$G$48)} -> 88381671 | L6: {=IF(J6<0,0,J6*'Info - danh-muc-2026-03-17 5-1'!$G$49)} -> 44190836 | M6: {='Info - danh-muc-2026-03-17 5-1'!$G$50*J6} -> 44190836 | N6: {=J6-K6-L6-M6} -> 2.6514501e+08
A7: 2030 | B7: {=B6+H7+I7-J7-D7+F7+G7+E7} -> 5.5121022e+08 | C7: 1000000000 | D7: {=-C6+C7} -> 0 | E7: {='Income - Expense - INCOME'!B7} -> 2.5715606e+09 | F7: {='Income - Expense - INCOME'!C7} -> 0 | G7: {=-E7*70%} -> -1.8000924e+09 | H7: {='Bank - INTEREST & LOAN'!B7} -> -220257950 | I7: {='Income - Expense - INCOME'!K7} -> 0 | J7: {=B6-D7} -> 4.7857997e+08 | K7: {=IF(J7<0,0,J7*'Info - danh-muc-2026-03-17 5-1'!$G$48)} -> 95715993 | L7: {=IF(J7<0,0,J7*'Info - danh-muc-2026-03-17 5-1'!$G$49)} -> 47857997 | M7: {='Info - danh-muc-2026-03-17 5-1'!$G$50*J7} -> 47857997 | N7: {=J7-K7-L7-M7} -> 2.8714798e+08
A8: 2031 | B8: {=B7+H8+I8-J8-D8+F8+G8+E8} -> 5.630857e+08 | C8: 1000000000 | D8: {=-C7+C8} -> 0 | E8: {='Income - Expense - INCOME'!B8} -> 2.6111455e+09 | F8: {='Income - Expense - INCOME'!C8} -> 0 | G8: {=-E8*70%} -> -1.8278019e+09 | H8: {='Bank - INTEREST & LOAN'!B8} -> -220257950 | I8: {='Income - Expense - INCOME'!K8} -> 0 | J8: {=B7-D8} -> 5.5121022e+08 | K8: {=IF(J8<0,0,J8*'Info - danh-muc-2026-03-17 5-1'!$G$48)} -> 1.1024204e+08 | L8: {=IF(J8<0,0,J8*'Info - danh-muc-2026-03-17 5-1'!$G$49)} -> 55121022 | M8: {='Info - danh-muc-2026-03-17 5-1'!$G$50*J8} -> 55121022 | N8: {=J8-K8-L8-M8} -> 3.3072613e+08
A9: 2032 | B9: {=B8+H9+I9-J9-D9+F9+G9+E9} -> 5.7543621e+08 | C9: 1000000000 | D9: {=-C8+C9} -> 0 | E9: {='Income - Expense - INCOME'!B9} -> 2.6523139e+09 | F9: {='Income - Expense - INCOME'!C9} -> 0 | G9: {=-E9*70%} -> -1.8566197e+09 | H9: {='Bank - INTEREST & LOAN'!B9} -> -220257950 | I9: {='Income - Expense - INCOME'!K9} -> 0 | J9: {=B8-D9} -> 5.630857e+08 | K9: {=IF(J9<0,0,J9*'Info - danh-muc-2026-03-17 5-1'!$G$48)} -> 1.1261714e+08 | L9: {=IF(J9<0,0,J9*'Info - danh-muc-2026-03-17 5-1'!$G$49)} -> 56308570 | M9: {='Info - danh-muc-2026-03-17 5-1'!$G$50*J9} -> 56308570 | N9: {=J9-K9-L9-M9} -> 3.3785142e+08
A10: 2033 | B10: {=B9+H10+I10-J10-D10+F10+G10+E10} -> 5.8828074e+08 | C10: 1000000000 | D10: {=-C9+C10} -> 0 | E10: {='Income - Expense - INCOME'!B10} -> 2.695129e+09 | F10: {='Income - Expense - INCOME'!C10} -> 0 | G10: {=-E10*70%} -> -1.8865903e+09 | H10: {='Bank - INTEREST & LOAN'!B10} -> -220257950 | I10: {='Income - Expense - INCOME'!K10} -> 0 | J10: {=B9-D10} -> 5.7543621e+08 | K10: {=IF(J10<0,0,J10*'Info - danh-muc-2026-03-17 5-1'!$G$48)} -> 1.1508724e+08 | L10: {=IF(J10<0,0,J10*'Info - danh-muc-2026-03-17 5-1'!$G$49)} -> 57543621 | M10: {='Info - danh-muc-2026-03-17 5-1'!$G$50*J10} -> 57543621 | N10: {=J10-K10-L10-M10} -> 3.4526173e+08
A11: 2034 | B11: {=B10+H11+I11-J11-D11+F11+G11+E11} -> 6.0163905e+08 | C11: 1000000000 | D11: {=-C10+C11} -> 0 | E11: {='Income - Expense - INCOME'!B11} -> 2.7396567e+09 | F11: {='Income - Expense - INCOME'!C11} -> 0 | G11: {=-E11*70%} -> -1.9177597e+09 | H11: {='Bank - INTEREST & LOAN'!B11} -> -220257950 | I11: {='Income - Expense - INCOME'!K11} -> 0 | J11: {=B10-D11} -> 5.8828074e+08 | K11: {=IF(J11<0,0,J11*'Info - danh-muc-2026-03-17 5-1'!$G$48)} -> 1.1765615e+08 | L11: {=IF(J11<0,0,J11*'Info - danh-muc-2026-03-17 5-1'!$G$49)} -> 58828074 | M11: {='Info - danh-muc-2026-03-17 5-1'!$G$50*J11} -> 58828074 | N11: {=J11-K11-L11-M11} -> 3.5296844e+08
A12: 2035 | B12: {=B11+H12+I12-J12-D12+F12+G12+E12} -> 6.1553169e+08 | C12: 1000000000 | D12: {=-C11+C12} -> 0 | E12: {='Income - Expense - INCOME'!B12} -> 2.7859655e+09 | F12: {='Income - Expense - INCOME'!C12} -> 0 | G12: {=-E12*70%} -> -1.9501758e+09 | H12: {='Bank - INTEREST & LOAN'!B12} -> -220257950 | I12: {='Income - Expense - INCOME'!K12} -> 0 | J12: {=B11-D12} -> 6.0163905e+08 | K12: {=IF(J12<0,0,J12*'Info - danh-muc-2026-03-17 5-1'!$G$48)} -> 1.2032781e+08 | L12: {=IF(J12<0,0,J12*'Info - danh-muc-2026-03-17 5-1'!$G$49)} -> 60163905 | M12: {='Info - danh-muc-2026-03-17 5-1'!$G$50*J12} -> 60163905 | N12: {=J12-K12-L12-M12} -> 3.6098343e+08
A13: 2036 | B13: {=B12+H13+I13-J13-D13+F13+G13+E13} -> 6.2998003e+08 | C13: 1000000000 | D13: {=-C12+C13} -> 0 | E13: {='Income - Expense - INCOME'!B13} -> 2.8341266e+09 | F13: {='Income - Expense - INCOME'!C13} -> 0 | G13: {=-E13*70%} -> -1.9838886e+09 | H13: {='Bank - INTEREST & LOAN'!B13} -> -220257950 | I13: {='Income - Expense - INCOME'!K13} -> 0 | J13: {=B12-D13} -> 6.1553169e+08 | K13: {=IF(J13<0,0,J13*'Info - danh-muc-2026-03-17 5-1'!$G$48)} -> 1.2310634e+08 | L13: {=IF(J13<0,0,J13*'Info - danh-muc-2026-03-17 5-1'!$G$49)} -> 61553169 | M13: {='Info - danh-muc-2026-03-17 5-1'!$G$50*J13} -> 61553169 | N13: {=J13-K13-L13-M13} -> 3.6931901e+08
A14: 2037 | B14: {=B13+H14+I14-J14-D14+F14+G14+E14} -> 6.4500631e+08 | C14: 1000000000 | D14: {=-C13+C14} -> 0 | E14: {='Income - Expense - INCOME'!B14} -> 2.8842142e+09 | F14: {='Income - Expense - INCOME'!C14} -> 0 | G14: {=-E14*70%} -> -2.0189499e+09 | H14: {='Bank - INTEREST & LOAN'!B14} -> -220257950 | I14: {='Income - Expense - INCOME'!K14} -> 0 | J14: {=B13-D14} -> 6.2998003e+08 | K14: {=IF(J14<0,0,J14*'Info - danh-muc-2026-03-17 5-1'!$G$48)} -> 1.2599601e+08 | L14: {=IF(J14<0,0,J14*'Info - danh-muc-2026-03-17 5-1'!$G$49)} -> 62998003 | M14: {='Info - danh-muc-2026-03-17 5-1'!$G$50*J14} -> 62998003 | N14: {=J14-K14-L14-M14} -> 3.7798802e+08
A15: 2038 | B15: {=B14+H15+I15-J15-D15+F15+G15+E15} -> 6.2510849e+08 | C15: 1000000000 | D15: {=-C14+C15} -> 0 | E15: {='Income - Expense - INCOME'!B15} -> 2.8178881e+09 | F15: {='Income - Expense - INCOME'!C15} -> 0 | G15: {=-E15*70%} -> -1.9725217e+09 | H15: {='Bank - INTEREST & LOAN'!B15} -> -220257950 | I15: {='Income - Expense - INCOME'!K15} -> 0 | J15: {=B14-D15} -> 6.4500631e+08 | K15: {=IF(J15<0,0,J15*'Info - danh-muc-2026-03-17 5-1'!$G$48)} -> 1.2900126e+08 | L15: {=IF(J15<0,0,J15*'Info - danh-muc-2026-03-17 5-1'!$G$49)} -> 64500631 | M15: {='Info - danh-muc-2026-03-17 5-1'!$G$50*J15} -> 64500631 | N15: {=J15-K15-L15-M15} -> 3.8700379e+08
A16: 2039 | B16: {=B15+H16+I16-J16-D16+F16+G16+E16} -> 6.4136092e+08 | C16: 1000000000 | D16: {=-C15+C16} -> 0 | E16: {='Income - Expense - INCOME'!B16} -> 2.8720629e+09 | F16: {='Income - Expense - INCOME'!C16} -> 0 | G16: {=-E16*70%} -> -2.010444e+09 | H16: {='Bank - INTEREST & LOAN'!B16} -> -220257950 | I16: {='Income - Expense - INCOME'!K16} -> 0 | J16: {=B15-D16} -> 6.2510849e+08 | K16: {=IF(J16<0,0,J16*'Info - danh-muc-2026-03-17 5-1'!$G$48)} -> 1.250217e+08 | L16: {=IF(J16<0,0,J16*'Info - danh-muc-2026-03-17 5-1'!$G$49)} -> 62510849 | M16: {='Info - danh-muc-2026-03-17 5-1'!$G$50*J16} -> 62510849 | N16: {=J16-K16-L16-M16} -> 3.750651e+08
A17: 2040 | B17: {=B16+H17+I17-J17-D17+F17+G17+E17} -> 6.5826344e+08 | C17: 1000000000 | D17: {=-C16+C17} -> 0 | E17: {='Income - Expense - INCOME'!B17} -> 2.9284046e+09 | F17: {='Income - Expense - INCOME'!C17} -> 0 | G17: {=-E17*70%} -> -2.0498832e+09 | H17: {='Bank - INTEREST & LOAN'!B17} -> -220257950 | I17: {='Income - Expense - INCOME'!K17} -> 0 | J17: {=B16-D17} -> 6.4136092e+08 | K17: {=IF(J17<0,0,J17*'Info - danh-muc-2026-03-17 5-1'!$G$48)} -> 1.2827218e+08 | L17: {=IF(J17<0,0,J17*'Info - danh-muc-2026-03-17 5-1'!$G$49)} -> 64136092 | M17: {='Info - danh-muc-2026-03-17 5-1'!$G$50*J17} -> 64136092 | N17: {=IF(J17<0,0,J17-K17-L17-M17)} -> 3.8481655e+08
A18: 2041 | B18: {=B17+H18+I18-J18-D18+F18+G18+E18} -> 6.7584206e+08 | C18: 1000000000 | D18: {=-C17+C18} -> 0 | E18: {='Income - Expense - INCOME'!B18} -> 2.987e+09 | F18: {='Income - Expense - INCOME'!C18} -> 0 | G18: {=-E18*70%} -> -2.0909e+09 | H18: {='Bank - INTEREST & LOAN'!B18} -> -220257950 | I18: {='Income - Expense - INCOME'!K18} -> 0 | J18: {=B17-D18} -> 6.5826344e+08 | K18: {=IF(J18<0,0,J18*'Info - danh-muc-2026-03-17 5-1'!$G$48)} -> 1.3165269e+08 | L18: {=IF(J18<0,0,J18*'Info - danh-muc-2026-03-17 5-1'!$G$49)} -> 65826344 | M18: {='Info - danh-muc-2026-03-17 5-1'!$G$50*J18} -> 65826344 | N18: {=IF(J18<0,0,J18-K18-L18-M18)} -> 3.9495806e+08
A19: 2042 | B19: {=B18+H19+I19-J19-D19+F19+G19+E19} -> 6.9412383e+08 | C19: 1000000000 | D19: {=-C18+C19} -> 0 | E19: {='Income - Expense - INCOME'!B19} -> 3.0479393e+09 | F19: {='Income - Expense - INCOME'!C19} -> 0 | G19: {=-E19*70%} -> -2.1335575e+09 | H19: {='Bank - INTEREST & LOAN'!B19} -> -220257950 | I19: {='Income - Expense - INCOME'!K19} -> 0 | J19: {=B18-D19} -> 6.7584206e+08 | K19: {=IF(J19<0,0,J19*'Info - danh-muc-2026-03-17 5-1'!$G$48)} -> 1.3516841e+08 | L19: {=IF(J19<0,0,J19*'Info - danh-muc-2026-03-17 5-1'!$G$49)} -> 67584206 | M19: {='Info - danh-muc-2026-03-17 5-1'!$G$50*J19} -> 67584206 | N19: {=IF(J19<0,0,J19-K19-L19-M19)} -> 4.0550524e+08
A20: 2043 | B20: {=B19+H20+I20-J20-D20+F20+G20+E20} -> 7.1313687e+08 | C20: 1000000000 | D20: {=-C19+C20} -> 0 | E20: {='Income - Expense - INCOME'!B20} -> 3.1113161e+09 | F20: {='Income - Expense - INCOME'!C20} -> 0 | G20: {=-E20*70%} -> -2.1779212e+09 | H20: {='Bank - INTEREST & LOAN'!B20} -> -220257950 | I20: {='Income - Expense - INCOME'!K20} -> 0 | J20: {=B19-D20} -> 6.9412383e+08 | K20: {=IF(J20<0,0,J20*'Info - danh-muc-2026-03-17 5-1'!$G$48)} -> 1.3882477e+08 | L20: {=IF(J20<0,0,J20*'Info - danh-muc-2026-03-17 5-1'!$G$49)} -> 69412383 | M20: {='Info - danh-muc-2026-03-17 5-1'!$G$50*J20} -> 69412383 | N20: {=IF(J20<0,0,J20-K20-L20-M20)} -> 4.164743e+08
A21: 2044 | B21: {=B20+H21+I21-J21-D21+F21+G21+E21} -> 7.3291043e+08 | C21: 1000000000 | D21: {=-C20+C21} -> 0 | E21: {='Income - Expense - INCOME'!B21} -> 3.1772279e+09 | F21: {='Income - Expense - INCOME'!C21} -> 0 | G21: {=-E21*70%} -> -2.2240596e+09 | H21: {='Bank - INTEREST & LOAN'!B21} -> -220257950 | I21: {='Income - Expense - INCOME'!K21} -> 0 | J21: {=B20-D21} -> 7.1313687e+08 | K21: {=IF(J21<0,0,J21*'Info - danh-muc-2026-03-17 5-1'!$G$48)} -> 1.4262737e+08 | L21: {=IF(J21<0,0,J21*'Info - danh-muc-2026-03-17 5-1'!$G$49)} -> 71313687 | M21: {='Info - danh-muc-2026-03-17 5-1'!$G$50*J21} -> 71313687 | N21: {=IF(J21<0,0,J21-K21-L21-M21)} -> 4.2788212e+08

Sheet Income - Expense - INCOME
A1: INCOME
B2: Income | C2: Tổng Thu khác | D2: Lương KK | E2: Lương SC | F2: Warehouse for rent | G2: Tiền thuê KK | H2: Cty | I2: Bán đất ở | J2: Thu khác | K2: Other expense | L2: Mua BDS | M2: Vay | N2: Investment | O2: Du hoc
A3: 2026 | B3: {=SUM(D3:H3)} -> 2.0246486e+09 | C3: {=I3+J3} -> 0 | D3: 216000000 | E3: 90000000 | G3: {=519168000*(1+4%)} -> 539934720 | H3: 1.1787138e+09 | K3: {=SUM(L3:O3)} -> 0
A4: 2027 | B4: {=SUM(D4:H4)} -> 2.058698e+09 | C4: {=I4+J4} -> 0 | D4: {=D3*(1+4%)} -> 224640000 | E4: {=E3*(1+4%)} -> 93600000 | G4: {=G3*(1+4%)} -> 5.6153211e+08 | H4: 1.1789259e+09 | K4: {=SUM(L4:O4)} -> 0
A5: 2028 | B5: {=SUM(D5:H5)} -> 2.207221e+09 | C5: {=I5+J5} -> 0 | D5: {=D4*(1+4%)} -> 233625600 | E5: {=E4*(1+4%)} -> 97344000 | G5: {=G4*(1+4%)} -> 5.8399339e+08 | H5: 1.292258e+09 | K5: {=SUM(L5:O5)} -> 0
A6: 2029 | B6: {=SUM(D6:H6)} -> 2.3294597e+09 | C6: {=I6+J6} -> 0 | D6: {=D5*(1+4%)} -> 242970624 | E6: {=E5*(1+4%)} -> 101237760 | G6: {=G5*(1+4%)} -> 6.0735313e+08 | H6: 1.3778982e+09 | K6: {=SUM(L6:O6)} -> 0
A7: 2030 | B7: {=SUM(D7:H7)} -> 2.5715606e+09 | C7: {=I7+J7} -> 0 | D7: {=D6*(1+4%)} -> 2.5268945e+08 | E7: {=E6*(1+4%)} -> 1.0528727e+08 | G7: {=G6*(1+4%)} -> 6.3164725e+08 | H7: 1.5819366e+09 | K7: {=SUM(L7:O7)} -> 0
A8: 2031 | B8: {=SUM(D8:H8)} -> 2.6111455e+09 | C8: {=I8+J8} -> 0 | D8: {=D7*(1+4%)} -> 2.6279703e+08 | E8: {=E7*(1+4%)} -> 1.0949876e+08 | G8: {=G7*(1+4%)} -> 6.5691314e+08 | H8: 1.5819366e+09 | K8: {=SUM(L8:O8)} -> 0
A9: 2032 | B9: {=SUM(D9:H9)} -> 2.6523139e+09 | C9: {=I9+J9} -> 0 | D9: {=D8*(1+4%)} -> 2.7330891e+08 | E9: {=E8*(1+4%)} -> 1.1387871e+08 | G9: {=G8*(1+4%)} -> 6.8318967e+08 | H9: 1.5819366e+09 | K9: {=SUM(L9:O9)} -> 0
A10: 2033 | B10: {=SUM(D10:H10)} -> 2.695129e+09 | C10: {=I10+J10} -> 0 | D10: {=D9*(1+4%)} -> 2.8424126e+08 | E10: {=E9*(1+4%)} -> 1.1843386e+08 | G10: {=G9*(1+4%)} -> 7.1051726e+08 | H10: 1.5819366e+09 | K10: {=SUM(L10:O10)} -> 0
A11: 2034 | B11: {=SUM(D11:H11)} -> 2.7396567e+09 | C11: {=I11+J11} -> 0 | D11: {=D10*(1+4%)} -> 2.9561091e+08 | E11: {=E10*(1+4%)} -> 1.2317121e+08 | G11: {=G10*(1+4%)} -> 7.3893795e+08 | H11: 1.5819366e+09 | K11: {=SUM(L11:O11)} -> 0
A12: 2035 | B12: {=SUM(D12:H12)} -> 2.7859655e+09 | C12: {=I12+J12} -> 0 | D12: {=D11*(1+4%)} -> 3.0743535e+08 | E12: {=E11*(1+4%)} -> 1.2809806e+08 | G12: {=G11*(1+4%)} -> 7.6849546e+08 | H12: 1.5819366e+09 | K12: {=SUM(L12:O12)} -> 0
A13: 2036 | B13: {=SUM(D13:H13)} -> 2.8341266e+09 | C13: {=I13+J13} -> 0 | D13: {=D12*(1+4%)} -> 3.1973277e+08 | E13: {=E12*(1+4%)} -> 1.3322199e+08 | G13: {=G12*(1+4%)} -> 7.9923528e+08 | H13: 1.5819366e+09 | K13: {=SUM(L13:O13)} -> 0
A14: 2037 | B14: {=SUM(D14:H14)} -> 2.8842142e+09 | C14: {=I14+J14} -> 0 | D14: {=D13*(1+4%)} -> 3.3252208e+08 | E14: {=E13*(1+4%)} -> 1.3855087e+08 | G14: {=G13*(1+4%)} -> 8.3120469e+08 | H14: 1.5819366e+09 | K14: {=SUM(L14:O14)} -> 0
A15: 2038 | B15: {=SUM(D15:H15)} -> 2.8178881e+09 | C15: {=I15+J15} -> 0 | D15: {=D14*(1+4%)} -> 3.4582296e+08 | E15: {=E14*(1+4%)} -> 1.440929e+08 | G15: {=G14*(1+4%)} -> 8.6445288e+08 | H15: 1.4635194e+09 | K15: {=SUM(L15:O15)} -> 0
... A21: 2044 | B21: {=SUM(D21:H21)} -> 3.1772279e+09 | C21: {=I21+J21} -> 0 | D21: {=D20*(1+4%)} -> 4.3757637e+08 | E21: {=E20*(1+4%)} -> 1.8232349e+08 | G21: {=G20*(1+4%)} -> 1.0938087e+09 | H21: 1.4635194e+09 | K21: {=SUM(L21:O21)} -> 0
O22: {=SUM(O3:O21)} -> 0

Sheet Bank - INTEREST & LOAN
A1: INTEREST & LOAN
B2: Total interest | C2: Total loan | D2: Dài hạn | E2: Cá nhân | F2: Lãi dài hạn | G2: Lãi cá nhân | H2: Gốc vay dài hạn | I2: Vay dài hạn BDS | J2: Luỹ kế vay dài hạn
A3: 2026 | B3: {=F3+G3} -> -80000000 | C3: {=I3+H3+D3+E3} -> -1683278000 | D3: -1335790000 | E3: -347488000 | F3: 0 | G3: -80000000 | J3: {=I3+H3} -> 0
A4: 2027 | B4: {=F4+G4} -> -220257950 | C4: {=I4+H4+D4+E4} -> -1683278000 | D4: {=D3} -> -1335790000 | E4: {=E3} -> -347488000 | F4: {=D3*'Info - danh-muc-2026-03-17 5-1'!$F$39} -> -140257950 | G4: {=G3} -> -80000000 | H4: {=H$22*J3} -> 0 | J4: {=J3+I4+H4} -> 0
A5: 2028 | B5: {=F5+G5} -> -220257950 | C5: {=I5+H5+D5+E5} -> -1683278000 | D5: {=D4} -> -1335790000 | E5: {=E4} -> -347488000 | F5: {=D4*'Info - danh-muc-2026-03-17 5-1'!$F$39} -> -140257950 | G5: {=G4} -> -80000000 | H5: {=H$22*J4} -> 0 | J5: {=J4+I5+H5} -> 0
A6: 2029 | B6: {=F6+G6} -> -220257950 | C6: {=I6+H6+D6+E6} -> -1683278000 | D6: {=D5} -> -1335790000 | E6: {=E5} -> -347488000 | F6: {=D5*'Info - danh-muc-2026-03-17 5-1'!$F$39} -> -140257950 | G6: {=G5} -> -80000000 | H6: {=H$22*J5} -> 0 | J6: {=J5+I6+H6} -> 0
A7: 2030 | B7: {=F7+G7} -> -220257950 | C7: {=I7+H7+D7+E7} -> -1683278000 | D7: {=D6} -> -1335790000 | E7: {=E6} -> -347488000 | F7: {=D6*'Info - danh-muc-2026-03-17 5-1'!$F$39} -> -140257950 | G7: {=G6} -> -80000000 | H7: {=H$22*J6} -> 0 | J7: {=J6+I7+H7} -> 0
A8: 2031 | B8: {=F8+G8} -> -220257950 | C8: {=I8+H8+D8+E8} -> -1683278000 | D8: {=D7} -> -1335790000 | E8: {=E7} -> -347488000 | F8: {=D7*'Info - danh-muc-2026-03-17 5-1'!$F$39} -> -140257950 | G8: {=G7} -> -80000000 | H8: {=H$22*J7} -> 0 | J8: {=J7+I8+H8} -> 0
A9: 2032 | B9: {=F9+G9} -> -220257950 | C9: {=I9+H9+D9+E9} -> -1683278000 | D9: {=D8} -> -1335790000 | E9: {=E8} -> -347488000 | F9: {=D8*'Info - danh-muc-2026-03-17 5-1'!$F$39} -> -140257950 | G9: {=G8} -> -80000000 | H9: {=H$22*J8} -> 0 | J9: {=J8+I9+H9} -> 0
A10: 2033 | B10: {=F10+G10} -> -220257950 | C10: {=I10+H10+D10+E10} -> -1683278000 | D10: {=D9} -> -1335790000 | E10: {=E9} -> -347488000 | F10: {=D9*'Info - danh-muc-2026-03-17 5-1'!$F$39} -> -140257950 | G10: {=G9} -> -80000000 | H10: {=H$22*J9} -> 0 | J10: {=J9+I10+H10} -> 0
A11: 2034 | B11: {=F11+G11} -> -220257950 | C11: {=I11+H11+D11+E11} -> -1683278000 | D11: {=D10} -> -1335790000 | E11: {=E10} -> -347488000 | F11: {=D10*'Info - danh-muc-2026-03-17 5-1'!$F$39} -> -140257950 | G11: {=G10} -> -80000000 | H11: {=H$22*J10} -> 0 | J11: {=J10+I11+H11} -> 0
A12: 2035 | B12: {=F12+G12} -> -220257950 | C12: {=I12+H12+D12+E12} -> -1683278000 | D12: {=D11} -> -1335790000 | E12: {=E11} -> -347488000 | F12: {=D11*'Info - danh-muc-2026-03-17 5-1'!$F$39} -> -140257950 | G12: {=G11} -> -80000000 | H12: {=H$22*J11} -> 0 | J12: {=J11+I12+H12} -> 0
A13: 2036 | B13: {=F13+G13} -> -220257950 | C13: {=I13+H13+D13+E13} -> -1683278000 | D13: {=D12} -> -1335790000 | E13: {=E12} -> -347488000 | F13: {=D12*'Info - danh-muc-2026-03-17 5-1'!$F$39} -> -140257950 | G13: {=G12} -> -80000000 | H13: {=H$22*J12} -> 0 | J13: {=J12+I13+H13} -> 0
A14: 2037 | B14: {=F14+G14} -> -220257950 | C14: {=I14+H14+D14+E14} -> -1683278000 | D14: {=D13} -> -1335790000 | E14: {=E13} -> -347488000 | F14: {=D13*'Info - danh-muc-2026-03-17 5-1'!$F$39} -> -140257950 | G14: {=G13} -> -80000000 | H14: {=H$22*J13} -> 0 | J14: {=J13+I14+H14} -> 0
A15: 2038 | B15: {=F15+G15} -> -220257950 | C15: {=I15+H15+D15+E15} -> -1683278000 | D15: {=D14} -> -1335790000 | E15: {=E14} -> -347488000 | F15: {=D14*'Info - danh-muc-2026-03-17 5-1'!$F$39} -> -140257950 | G15: {=G14} -> -80000000 | H15: {=H$22*J14} -> 0 | J15: {=J14+I15+H15} -> 0
... A21: 2044 | B21: {=F21+G21} -> -220257950 | C21: {=I21+H21+D21+E21} -> -1683278000 | D21: {=D20} -> -1335790000 | E21: {=E20} -> -347488000 | F21: {=D20*'Info - danh-muc-2026-03-17 5-1'!$F$39} -> -140257950 | G21: {=G20} -> -80000000 | H21: {=H$22*J20} -> 0 | J21: {=J20+I21+H21} -> 0
F22: {='Info - danh-muc-2026-03-17 5-1'!F39} -> 0.105 | H22: -0.05

Sheet Financial fund - CASH
B1: CASH
C2: Cash đầu năm | D2: cash lợi nhuận | E2: cash cuối năm | F2: Vàng đầu năm | G2: vàng lợi nhuận | H2: vàng cuối năm | I2: Stock đầu năm | J2: stock lợi nhuận | K2: stock cuối năm | L2: CCQ đầu năm | M2: ccq lợi nhuận | N2: ccq cuối năm | O2: Crypto đầu năm | P2: crypto lợi nhuận | Q2: crypto cuối năm
B3: 2026 | C3: {=1220000000+'Cash flow - CASH FLOW'!D3} -> 1000000000 | D3: {=C3*'Info - danh-muc-2026-03-17 5-1'!$F$32} -> 65000000 | E3: {=C3+D3} -> 1065000000 | F3: {=1497440000+'Cash flow - CASH FLOW'!K3} -> 2771609000 | G3: {=(F3)*'Info - danh-muc-2026-03-17 5-1'!$F$34} -> 221728720 | H3: {=F3+G3} -> 2993337720 | I3: {=2114622000+'Cash flow - CASH FLOW'!N3} -> 5937129000 | J3: {=I3*'Info - danh-muc-2026-03-17 5-1'!$F$44} -> 890569350 | K3: {=I3+J3} -> 6827698350 | L3: {=424726000+'Cash flow - CASH FLOW'!M3} -> 1061810500 | M3: {=L3*'Info - danh-muc-2026-03-17 5-1'!$F$41} -> 95562945 | N3: {=M3+L3} -> 1157373445 | O3: {=278175000+'Cash flow - CASH FLOW'!L3} -> 915259500 | P3: {=(O3)*'Info - danh-muc-2026-03-17 5-1'!$F$40} -> 137288925 | Q3: {=O3+P3} -> 1052548425
B4: 2027 | C4: {=E3+'Cash flow - CASH FLOW'!D4} -> 1065000000 | D4: {=C4*'Info - danh-muc-2026-03-17 5-1'!$F$32} -> 69225000 | E4: {=C4+D4} -> 1134225000 | F4: {=H3+'Cash flow - CASH FLOW'!K4} -> 3.0988166e+09 | G4: {=(F4)*'Info - danh-muc-2026-03-17 5-1'!$F$34} -> 2.4790533e+08 | H4: {=F4+G4} -> 3.346722e+09 | I4: {=K3+'Cash flow - CASH FLOW'!N4} -> 7.1441351e+09 | J4: {=I4*'Info - danh-muc-2026-03-17 5-1'!$F$44} -> 1.0716203e+09 | K4: {=I4+J4} -> 8.2157554e+09 | L4: {=N3+'Cash flow - CASH FLOW'!M4} -> 1.2101129e+09 | M4: {=L4*'Info - danh-muc-2026-03-17 5-1'!$F$41} -> 1.0891016e+08 | N4: {=M4+L4} -> 1.3190231e+09 | O4: {=Q3+'Cash flow - CASH FLOW'!L4} -> 1.1052879e+09 | P4: {=(O4)*'Info - danh-muc-2026-03-17 5-1'!$F$40} -> 1.6579318e+08 | Q4: {=O4+P4} -> 1.2710811e+09
B5: 2028 | C5: {=E4+'Cash flow - CASH FLOW'!D5} -> 1134225000 | D5: {=C5*'Info - danh-muc-2026-03-17 5-1'!$F$32} -> 73724625 | E5: {=C5+D5} -> 1207949625 | F5: {=H4+'Cash flow - CASH FLOW'!K5} -> 3.4261923e+09 | G5: {=(F5)*'Info - danh-muc-2026-03-17 5-1'!$F$34} -> 2.7409538e+08 | H5: {=F5+G5} -> 3.7002876e+09 | I5: {=K4+'Cash flow - CASH FLOW'!N5} -> 8.4541662e+09 | J5: {=I5*'Info - danh-muc-2026-03-17 5-1'!$F$44} -> 1.2681249e+09 | K5: {=I5+J5} -> 9.7222912e+09 | L5: {=N4+'Cash flow - CASH FLOW'!M5} -> 1.3587582e+09 | M5: {=L5*'Info - danh-muc-2026-03-17 5-1'!$F$41} -> 1.2228824e+08 | N5: {=M5+L5} -> 1.4810464e+09 | O5: {=Q4+'Cash flow - CASH FLOW'!L5} -> 1.3108162e+09 | P5: {=(O5)*'Info - danh-muc-2026-03-17 5-1'!$F$40} -> 1.9662243e+08 | Q5: {=O5+P5} -> 1.5074386e+09
B6: 2029 | C6: {=E5+'Cash flow - CASH FLOW'!D6} -> 1207949625 | D6: {=C6*'Info - danh-muc-2026-03-17 5-1'!$F$32} -> 78516726 | E6: {=C6+D6} -> 1.2864664e+09 | F6: {=H5+'Cash flow - CASH FLOW'!K6} -> 3.7886693e+09 | G6: {=(F6)*'Info - danh-muc-2026-03-17 5-1'!$F$34} -> 3.0309354e+08 | H6: {=F6+G6} -> 4.0917629e+09 | I6: {=K5+'Cash flow - CASH FLOW'!N6} -> 9.9874362e+09 | J6: {=I6*'Info - danh-muc-2026-03-17 5-1'!$F$44} -> 1.4981154e+09 | K6: {=I6+J6} -> 1.1485552e+10 | L6: {=N5+'Cash flow - CASH FLOW'!M6} -> 1.5252373e+09 | M6: {=L6*'Info - danh-muc-2026-03-17 5-1'!$F$41} -> 1.3727136e+08 | N6: {=M6+L6} -> 1.6625086e+09 | O6: {=Q5+'Cash flow - CASH FLOW'!L6} -> 1.5516295e+09 | P6: {=(O6)*'Info - danh-muc-2026-03-17 5-1'!$F$40} -> 2.3274442e+08 | Q6: {=O6+P6} -> 1.7843739e+09
B7: 2030 | C7: {=E6+'Cash flow - CASH FLOW'!D7} -> 1.2864664e+09 | D7: {=C7*'Info - danh-muc-2026-03-17 5-1'!$F$32} -> 83620313 | E7: {=C7+D7} -> 1.3700867e+09 | F7: {=H6+'Cash flow - CASH FLOW'!K7} -> 4.1874788e+09 | G7: {=(F7)*'Info - danh-muc-2026-03-17 5-1'!$F$34} -> 3.3499831e+08 | H7: {=F7+G7} -> 4.5224772e+09 | I7: {=K6+'Cash flow - CASH FLOW'!N7} -> 1.17727e+10 | J7: {=I7*'Info - danh-muc-2026-03-17 5-1'!$F$44} -> 1.7659049e+09 | K7: {=I7+J7} -> 1.3538605e+10 | L7: {=N6+'Cash flow - CASH FLOW'!M7} -> 1.7103666e+09 | M7: {=L7*'Info - danh-muc-2026-03-17 5-1'!$F$41} -> 1.53933e+08 | N7: {=M7+L7} -> 1.8642996e+09 | O7: {=Q6+'Cash flow - CASH FLOW'!L7} -> 1.8322319e+09 | P7: {=(O7)*'Info - danh-muc-2026-03-17 5-1'!$F$40} -> 2.7483478e+08 | Q7: {=O7+P7} -> 2.1070667e+09
B8: 2031 | C8: {=E7+'Cash flow - CASH FLOW'!D8} -> 1.3700867e+09 | D8: {=C8*'Info - danh-muc-2026-03-17 5-1'!$F$32} -> 89055633 | E8: {=C8+D8} -> 1.4591423e+09 | F8: {=H7+'Cash flow - CASH FLOW'!K8} -> 4.6327192e+09 | G8: {=(F8)*'Info - danh-muc-2026-03-17 5-1'!$F$34} -> 3.7061754e+08 | H8: {=F8+G8} -> 5.0033367e+09 | I8: {=K7+'Cash flow - CASH FLOW'!N8} -> 1.3869331e+10 | J8: {=I8*'Info - danh-muc-2026-03-17 5-1'!$F$44} -> 2.0803996e+09 | K8: {=I8+J8} -> 1.594973e+10 | L8: {=N7+'Cash flow - CASH FLOW'!M8} -> 1.9194207e+09 | M8: {=L8*'Info - danh-muc-2026-03-17 5-1'!$F$41} -> 1.7274786e+08 | N8: {=M8+L8} -> 2.0921685e+09 | O8: {=Q7+'Cash flow - CASH FLOW'!L8} -> 2.1621877e+09 | P8: {=(O8)*'Info - danh-muc-2026-03-17 5-1'!$F$40} -> 3.2432816e+08 | Q8: {=O8+P8} -> 2.4865159e+09
B9: 2032 | C9: {=E8+'Cash flow - CASH FLOW'!D9} -> 1.4591423e+09 | D9: {=C9*'Info - danh-muc-2026-03-17 5-1'!$F$32} -> 94844249 | E9: {=C9+D9} -> 1.5539865e+09 | F9: {=H8+'Cash flow - CASH FLOW'!K9} -> 5.1159539e+09 | G9: {=(F9)*'Info - danh-muc-2026-03-17 5-1'!$F$34} -> 4.0927631e+08 | H9: {=F9+G9} -> 5.5252302e+09 | I9: {=K8+'Cash flow - CASH FLOW'!N9} -> 1.6287582e+10 | J9: {=I9*'Info - danh-muc-2026-03-17 5-1'!$F$44} -> 2.4431373e+09 | K9: {=I9+J9} -> 1.8730719e+10 | L9: {=N8+'Cash flow - CASH FLOW'!M9} -> 2.1484771e+09 | M9: {=L9*'Info - danh-muc-2026-03-17 5-1'!$F$41} -> 1.9336294e+08 | N9: {=M9+L9} -> 2.34184e+09 | O9: {=Q8+'Cash flow - CASH FLOW'!L9} -> 2.5428244e+09 | P9: {=(O9)*'Info - danh-muc-2026-03-17 5-1'!$F$40} -> 3.8142366e+08 | Q9: {=O9+P9} -> 2.9242481e+09
B10: 2033 | C10: {=E9+'Cash flow - CASH FLOW'!D10} -> 1.5539865e+09 | D10: {=C10*'Info - danh-muc-2026-03-17 5-1'!$F$32} -> 1.0100913e+08 | E10: {=C10+D10} -> 1.6549957e+09 | F10: {=H9+'Cash flow - CASH FLOW'!K10} -> 5.6403174e+09 | G10: {=(F10)*'Info - danh-muc-2026-03-17 5-1'!$F$34} -> 4.5122539e+08 | H10: {=F10+G10} -> 6.0915428e+09 | I10: {=K9+'Cash flow - CASH FLOW'!N10} -> 1.9075981e+10 | J10: {=I10*'Info - danh-muc-2026-03-17 5-1'!$F$44} -> 2.8613971e+09 | K10: {=I10+J10} -> 2.1937378e+10 | L10: {=N9+'Cash flow - CASH FLOW'!M10} -> 2.3993836e+09 | M10: {=L10*'Info - danh-muc-2026-03-17 5-1'!$F$41} -> 2.1594453e+08 | N10: {=M10+L10} -> 2.6153282e+09 | O10: {=Q9+'Cash flow - CASH FLOW'!L10} -> 2.9817917e+09 | P10: {=(O10)*'Info - danh-muc-2026-03-17 5-1'!$F$40} -> 4.4726876e+08 | Q10: {=O10+P10} -> 3.4290605e+09
B11: 2034 | C11: {=E10+'Cash flow - CASH FLOW'!D11} -> 1.6549957e+09 | D11: {=C11*'Info - danh-muc-2026-03-17 5-1'!$F$32} -> 1.0757472e+08 | E11: {=C11+D11} -> 1.7625704e+09 | F11: {=H10+'Cash flow - CASH FLOW'!K11} -> 6.209199e+09 | G11: {=(F11)*'Info - danh-muc-2026-03-17 5-1'!$F$34} -> 4.9673592e+08 | H11: {=F11+G11} -> 6.7059349e+09 | I11: {=K10+'Cash flow - CASH FLOW'!N11} -> 2.2290346e+10 | J11: {=I11*'Info - danh-muc-2026-03-17 5-1'!$F$44} -> 3.3435519e+09 | K11: {=I11+J11} -> 2.5633898e+10 | L11: {=N10+'Cash flow - CASH FLOW'!M11} -> 2.6741562e+09 | M11: {=L11*'Info - danh-muc-2026-03-17 5-1'!$F$41} -> 2.4067406e+08 | N11: {=M11+L11} -> 2.9148303e+09 | O11: {=Q10+'Cash flow - CASH FLOW'!L11} -> 3.4878885e+09 | P11: {=(O11)*'Info - danh-muc-2026-03-17 5-1'!$F$40} -> 5.2318328e+08 | Q11: {=O11+P11} -> 4.0110718e+09
B12: 2035 | C12: {=E11+'Cash flow - CASH FLOW'!D12} -> 1.7625704e+09 | D12: {=C12*'Info - danh-muc-2026-03-17 5-1'!$F$32} -> 1.1456708e+08 | E12: {=C12+D12} -> 1.8771375e+09 | F12: {=H11+'Cash flow - CASH FLOW'!K12} -> 6.8262627e+09 | G12: {=(F12)*'Info - danh-muc-2026-03-17 5-1'!$F$34} -> 5.4610102e+08 | H12: {=F12+G12} -> 7.3723637e+09 | I12: {=K11+'Cash flow - CASH FLOW'!N12} -> 2.5994882e+10 | J12: {=I12*'Info - danh-muc-2026-03-17 5-1'!$F$44} -> 3.8992322e+09 | K12: {=I12+J12} -> 2.9894114e+10 | L12: {=N11+'Cash flow - CASH FLOW'!M12} -> 2.9749942e+09 | M12: {=L12*'Info - danh-muc-2026-03-17 5-1'!$F$41} -> 2.6774948e+08 | N12: {=M12+L12} -> 3.2427437e+09 | O12: {=Q11+'Cash flow - CASH FLOW'!L12} -> 4.0712357e+09 | P12: {=(O12)*'Info - danh-muc-2026-03-17 5-1'!$F$40} -> 6.1068536e+08 | Q12: {=O12+P12} -> 4.6819211e+09
B13: 2036 | C13: {=E12+'Cash flow - CASH FLOW'!D13} -> 1.8771375e+09 | D13: {=C13*'Info - danh-muc-2026-03-17 5-1'!$F$32} -> 1.2201394e+08 | E13: {=C13+D13} -> 1.9991514e+09 | F13: {=H12+'Cash flow - CASH FLOW'!K13} -> 7.49547e+09 | G13: {=(F13)*'Info - danh-muc-2026-03-17 5-1'!$F$34} -> 5.996376e+08 | H13: {=F13+G13} -> 8.0951077e+09 | I13: {=K12+'Cash flow - CASH FLOW'!N13} -> 3.0263433e+10 | J13: {=I13*'Info - danh-muc-2026-03-17 5-1'!$F$44} -> 4.5395149e+09 | K13: {=I13+J13} -> 3.4802948e+10 | L13: {=N12+'Cash flow - CASH FLOW'!M13} -> 3.3042969e+09 | M13: {=L13*'Info - danh-muc-2026-03-17 5-1'!$F$41} -> 2.9738672e+08 | N13: {=M13+L13} -> 3.6016836e+09 | O13: {=Q12+'Cash flow - CASH FLOW'!L13} -> 4.7434743e+09 | P13: {=(O13)*'Info - danh-muc-2026-03-17 5-1'!$F$40} -> 7.1152114e+08 | Q13: {=O13+P13} -> 5.4549954e+09
B14: 2037 | C14: {=E13+'Cash flow - CASH FLOW'!D14} -> 1.9991514e+09 | D14: {=C14*'Info - danh-muc-2026-03-17 5-1'!$F$32} -> 1.2994484e+08 | E14: {=C14+D14} -> 2.1290962e+09 | F14: {=H13+'Cash flow - CASH FLOW'!K14} -> 8.2211037e+09 | G14: {=(F14)*'Info - danh-muc-2026-03-17 5-1'!$F$34} -> 6.5768829e+08 | H14: {=F14+G14} -> 8.878792e+09 | I14: {=K13+'Cash flow - CASH FLOW'!N14} -> 3.5180936e+10 | J14: {=I14*'Info - danh-muc-2026-03-17 5-1'!$F$44} -> 5.2771404e+09 | K14: {=I14+J14} -> 4.0458076e+10 | L14: {=N13+'Cash flow - CASH FLOW'!M14} -> 3.6646816e+09 | M14: {=L14*'Info - danh-muc-2026-03-17 5-1'!$F$41} -> 3.2982134e+08 | N14: {=M14+L14} -> 3.9945029e+09 | O14: {=Q13+'Cash flow - CASH FLOW'!L14} -> 5.5179934e+09 | P14: {=(O14)*'Info - danh-muc-2026-03-17 5-1'!$F$40} -> 8.2769901e+08 | Q14: {=O14+P14} -> 6.3456924e+09
B15: 2038 | C15: {=E14+'Cash flow - CASH FLOW'!D15} -> 2.1290962e+09 | D15: {=C15*'Info - danh-muc-2026-03-17 5-1'!$F$32} -> 1.3839126e+08 | E15: {=C15+D15} -> 2.2674875e+09 | F15: {=H14+'Cash flow - CASH FLOW'!K15} -> 9.0077932e+09 | G15: {=(F15)*'Info - danh-muc-2026-03-17 5-1'!$F$34} -> 7.2062346e+08 | H15: {=F15+G15} -> 9.7284167e+09 | I15: {=K14+'Cash flow - CASH FLOW'!N15} -> 4.084508e+10 | J15: {=I15*'Info - danh-muc-2026-03-17 5-1'!$F$44} -> 6.126762e+09 | K15: {=I15+J15} -> 4.6971842e+10 | L15: {=N14+'Cash flow - CASH FLOW'!M15} -> 4.0590036e+09 | M15: {=L15*'Info - danh-muc-2026-03-17 5-1'!$F$41} -> 3.6531032e+08 | N15: {=M15+L15} -> 4.4243139e+09 | O15: {=Q14+'Cash flow - CASH FLOW'!L15} -> 6.410193e+09 | P15: {=(O15)*'Info - danh-muc-2026-03-17 5-1'!$F$40} -> 9.6152896e+08 | Q15: {=O15+P15} -> 7.371722e+09
... B21: 2044 | C21: {=E20+'Cash flow - CASH FLOW'!D21} -> 3.1066544e+09 | D21: {=C21*'Info - danh-muc-2026-03-17 5-1'!$F$32} -> 2.0193253e+08 | E21: {=C21+D21} -> 3.3085869e+09 | F21: {=H20+'Cash flow - CASH FLOW'!K21} -> 1.526851e+10 | G21: {=(F21)*'Info - danh-muc-2026-03-17 5-1'!$F$34} -> 1.2214808e+09 | H21: {=F21+G21} -> 1.648999e+10 | I21: {=K20+'Cash flow - CASH FLOW'!N21} -> 9.7948378e+10 | J21: {=I21*'Info - danh-muc-2026-03-17 5-1'!$F$44} -> 1.4692257e+10 | K21: {=I21+J21} -> 1.1264064e+11 | L21: {=N20+'Cash flow - CASH FLOW'!M21} -> 7.3065863e+09 | M21: {=L21*'Info - danh-muc-2026-03-17 5-1'!$F$41} -> 6.5759277e+08 | N21: {=M21+L21} -> 7.9641791e+09 | O21: {=Q20+'Cash flow - CASH FLOW'!L21} -> 1.5405704e+10 | P21: {=(O21)*'Info - danh-muc-2026-03-17 5-1'!$F$40} -> 2.3108556e+09 | Q21: {=O21+P21} -> 1.7716559e+10
